{
  "id": 111,
  "title": "Bölüm 111",
  "difficulty": "Kolay",
  "grid_size_r": 11,
  "grid_size_c": 8,
  "grid": [
    [
      0,
      0,
      0,
      0,
      0,
      0,
      1,
      0
    ],
    [
      0,
      0,
      0,
      0,
      1,
      1,
      1,
      1
    ],
    [
      0,
      0,
      0,
      0,
      0,
      0,
      1,
      0
    ],
    [
      0,
      0,
      0,
      0,
      0,
      0,
      1,
      0
    ],
    [
      0,
      0,
      1,
      1,
      1,
      1,
      1,
      0
    ],
    [
      0,
      0,
      0,
      1,
      0,
      1,
      0,
      1
    ],
    [
      0,
      0,
      0,
      1,
      0,
      1,
      0,
      1
    ],
    [
      1,
      1,
      1,
      1,
      0,
      1,
      1,
      1
    ],
    [
      0,
      1,
      0,
      1,
      0,
      0,
      0,
      1
    ],
    [
      0,
      1,
      0,
      0,
      0,
      0,
      0,
      0
    ],
    [
      0,
      1,
      0,
      0,
      0,
      0,
      0,
      0
    ]
  ],
  "words": [
    {
      "number": 1,
      "direction": "down",
      "row": 0,
      "col": 6,
      "length": 5,
      "clue": "Bir dağın en yüksek noktası; ulaşılabilecek en üst basamak (5 harf) [B111-S1]",
      "answer": "ZİRVE"
    },
    {
      "number": 2,
      "direction": "across",
      "row": 1,
      "col": 4,
      "length": 4,
      "clue": "Yetkili bir kimsenin yerine getirilmek üzere verdiği kesin buyruk (4 harf) [B111-S2]",
      "answer": "EMİR"
    },
    {
      "number": 3,
      "direction": "across",
      "row": 4,
      "col": 2,
      "length": 5,
      "clue": "Ev ya da yapı yakınında çiçek, sebze ve ağaç yetiştirilen yeşil alan (5 harf) [B111-S3]",
      "answer": "BAHÇE"
    },
    {
      "number": 4,
      "direction": "down",
      "row": 4,
      "col": 3,
      "length": 5,
      "clue": "Dünyanın farklı bölgelerini gösteren haritaların toplandığı büyük kitap (5 harf) [B111-S4]",
      "answer": "ATLAS"
    },
    {
      "number": 5,
      "direction": "down",
      "row": 4,
      "col": 5,
      "length": 4,
      "clue": "Birbirinin eşi olan iki şeyden oluşan takım; tekin karşıtı sayı grubu (4 harf) [B111-S5]",
      "answer": "ÇİFT"
    },
    {
      "number": 6,
      "direction": "down",
      "row": 5,
      "col": 7,
      "length": 4,
      "clue": "Bir ailenin oturduğu ev; aynı zamanda sayıdaki basamak anlamı taşır (4 harf) [B111-S6]",
      "answer": "HANE"
    },
    {
      "number": 7,
      "direction": "across",
      "row": 7,
      "col": 0,
      "length": 4,
      "clue": "Bir kesik ya da darbe sonucu bedende oluşan açık doku hasarı (4 harf) [B111-S7]",
      "answer": "YARA"
    },
    {
      "number": 8,
      "direction": "down",
      "row": 7,
      "col": 1,
      "length": 4,
      "clue": "Kırda ya da ormanda silahla veya tuzakla av peşinde koşan kişi (4 harf) [B111-S8]",
      "answer": "AVCI"
    },
    {
      "number": 9,
      "direction": "across",
      "row": 7,
      "col": 5,
      "length": 3,
      "clue": "İnsanın bedenini saran dış deri; vücudumuzun dış yüzü (3 harf) [B111-S9]",
      "answer": "TEN"
    }
  ]
}
