{
  "id": 10,
  "title": "Bölüm 10",
  "difficulty": "Kolay",
  "grid_size_r": 9,
  "grid_size_c": 10,
  "grid": [
    [
      0,
      0,
      0,
      0,
      0,
      0,
      1,
      0,
      0,
      0
    ],
    [
      0,
      0,
      0,
      0,
      0,
      0,
      1,
      0,
      0,
      0
    ],
    [
      0,
      0,
      0,
      0,
      1,
      1,
      1,
      1,
      0,
      0
    ],
    [
      1,
      1,
      1,
      1,
      1,
      0,
      0,
      0,
      0,
      0
    ],
    [
      0,
      0,
      1,
      0,
      1,
      0,
      0,
      0,
      0,
      0
    ],
    [
      1,
      1,
      1,
      0,
      1,
      0,
      0,
      1,
      0,
      1
    ],
    [
      0,
      0,
      1,
      0,
      1,
      1,
      1,
      1,
      0,
      1
    ],
    [
      0,
      0,
      0,
      0,
      0,
      0,
      0,
      1,
      0,
      1
    ],
    [
      0,
      0,
      0,
      0,
      0,
      1,
      1,
      1,
      1,
      1
    ]
  ],
  "words": [
    {
      "number": 1,
      "direction": "down",
      "row": 0,
      "col": 6,
      "length": 3,
      "clue": "Mekan, konum",
      "answer": "YER"
    },
    {
      "number": 2,
      "direction": "down",
      "row": 2,
      "col": 4,
      "length": 5,
      "clue": "Aydınlatma aracı",
      "answer": "LAMBA"
    },
    {
      "number": 2,
      "direction": "across",
      "row": 2,
      "col": 4,
      "length": 4,
      "clue": "Türk parası",
      "answer": "LİRA"
    },
    {
      "number": 3,
      "direction": "across",
      "row": 3,
      "col": 0,
      "length": 5,
      "clue": "En küçük işaret",
      "answer": "NOKTA"
    },
    {
      "number": 4,
      "direction": "down",
      "row": 3,
      "col": 2,
      "length": 4,
      "clue": "Siyah renk",
      "answer": "KARA"
    },
    {
      "number": 5,
      "direction": "across",
      "row": 5,
      "col": 0,
      "length": 3,
      "clue": "Eflatun renk",
      "answer": "MOR"
    },
    {
      "number": 6,
      "direction": "down",
      "row": 5,
      "col": 7,
      "length": 4,
      "clue": "Ateşin parlak kısmı",
      "answer": "ALEV"
    },
    {
      "number": 7,
      "direction": "down",
      "row": 5,
      "col": 9,
      "length": 4,
      "clue": "Solunan gaz",
      "answer": "HAVA"
    },
    {
      "number": 8,
      "direction": "across",
      "row": 6,
      "col": 4,
      "length": 4,
      "clue": "Gerçek, hakiki",
      "answer": "ASIL"
    },
    {
      "number": 9,
      "direction": "across",
      "row": 8,
      "col": 5,
      "length": 5,
      "clue": "Zar masa oyunu",
      "answer": "TAVLA"
    }
  ]
}