{
  "id": 171,
  "title": "Bölüm 171",
  "difficulty": "Orta",
  "grid_size_r": 10,
  "grid_size_c": 11,
  "grid": [
    [
      0,
      0,
      0,
      0,
      0,
      0,
      1,
      0,
      0,
      0,
      0
    ],
    [
      0,
      0,
      0,
      0,
      1,
      1,
      1,
      1,
      1,
      0,
      0
    ],
    [
      0,
      0,
      0,
      0,
      0,
      0,
      1,
      0,
      0,
      0,
      0
    ],
    [
      0,
      0,
      1,
      1,
      1,
      1,
      1,
      0,
      1,
      0,
      0
    ],
    [
      0,
      0,
      0,
      0,
      1,
      0,
      0,
      0,
      1,
      0,
      0
    ],
    [
      0,
      0,
      0,
      0,
      1,
      1,
      1,
      1,
      1,
      0,
      0
    ],
    [
      0,
      0,
      1,
      0,
      1,
      0,
      0,
      0,
      1,
      1,
      1
    ],
    [
      0,
      1,
      1,
      1,
      1,
      0,
      0,
      0,
      1,
      0,
      0
    ],
    [
      0,
      0,
      1,
      0,
      1,
      0,
      0,
      0,
      1,
      0,
      0
    ],
    [
      1,
      1,
      1,
      1,
      0,
      0,
      0,
      0,
      0,
      0,
      0
    ]
  ],
  "words": [
    {
      "number": 1,
      "direction": "down",
      "row": 0,
      "col": 6,
      "length": 4,
      "clue": "Günlük dilde Bacak ucu olarak bilinen kavram",
      "answer": "AYAK"
    },
    {
      "number": 2,
      "direction": "across",
      "row": 1,
      "col": 4,
      "length": 5,
      "clue": "Günlük dilde Ölçü ya da ebat olarak bilinen kavram",
      "answer": "BOYUT"
    },
    {
      "number": 3,
      "direction": "across",
      "row": 3,
      "col": 2,
      "length": 5,
      "clue": "Üflemeli ses aleti karşılığı olarak kullanılan kelime",
      "answer": "DÜDÜK"
    },
    {
      "number": 4,
      "direction": "down",
      "row": 3,
      "col": 4,
      "length": 6,
      "clue": "Ülke yönetimi için kullanılan yaygın ifade",
      "answer": "DEVLET"
    },
    {
      "number": 5,
      "direction": "down",
      "row": 3,
      "col": 8,
      "length": 6,
      "clue": "Konular listesi için kullanılan yaygın ifade",
      "answer": "GÜNDEM"
    },
    {
      "number": 6,
      "direction": "across",
      "row": 5,
      "col": 4,
      "length": 5,
      "clue": "Bulmacada Yurt ya da memleket karşılığını veren yanıt",
      "answer": "VATAN"
    },
    {
      "number": 7,
      "direction": "down",
      "row": 6,
      "col": 2,
      "length": 4,
      "clue": "Üçten sonra gelen için kullanılan yaygın ifade",
      "answer": "DÖRT"
    },
    {
      "number": 8,
      "direction": "across",
      "row": 6,
      "col": 8,
      "length": 3,
      "clue": "Bulmacada Çiğneme organı karşılığını veren yanıt",
      "answer": "DİŞ"
    },
    {
      "number": 9,
      "direction": "across",
      "row": 7,
      "col": 1,
      "length": 4,
      "clue": "Günlük dilde Yüzeylerin birleşimi olarak bilinen kavram",
      "answer": "KÖŞE"
    },
    {
      "number": 10,
      "direction": "across",
      "row": 9,
      "col": 0,
      "length": 4,
      "clue": "Üstünü kapatan karşılığı olarak kullanılan kelime",
      "answer": "ÖRTÜ"
    }
  ]
}
