{
  "id": 288,
  "title": "Bölüm 288",
  "difficulty": "Zor",
  "grid_size_r": 9,
  "grid_size_c": 12,
  "grid": [
    [
      0,
      1,
      0,
      0,
      0,
      0,
      0,
      0,
      0,
      0,
      0,
      0
    ],
    [
      0,
      1,
      0,
      0,
      0,
      0,
      0,
      0,
      0,
      0,
      0,
      0
    ],
    [
      0,
      1,
      0,
      1,
      0,
      1,
      0,
      0,
      0,
      0,
      0,
      0
    ],
    [
      1,
      1,
      1,
      1,
      1,
      1,
      0,
      0,
      0,
      0,
      0,
      0
    ],
    [
      1,
      0,
      0,
      1,
      0,
      1,
      0,
      0,
      1,
      0,
      1,
      0
    ],
    [
      1,
      1,
      1,
      0,
      0,
      1,
      1,
      1,
      1,
      0,
      1,
      0
    ],
    [
      0,
      0,
      0,
      0,
      0,
      0,
      0,
      0,
      1,
      0,
      1,
      0
    ],
    [
      0,
      0,
      0,
      0,
      0,
      0,
      0,
      1,
      1,
      1,
      1,
      1
    ],
    [
      0,
      0,
      0,
      0,
      0,
      0,
      0,
      0,
      0,
      0,
      1,
      0
    ]
  ],
  "words": [
    {
      "number": 1,
      "direction": "down",
      "row": 0,
      "col": 1,
      "length": 4,
      "clue": "Baş ya da kelle için kullanılan yaygın ifade",
      "answer": "KAFA"
    },
    {
      "number": 2,
      "direction": "down",
      "row": 2,
      "col": 3,
      "length": 3,
      "clue": "Bulmacada Çiğneme organı karşılığını veren yanıt",
      "answer": "DİŞ"
    },
    {
      "number": 3,
      "direction": "down",
      "row": 2,
      "col": 5,
      "length": 4,
      "clue": "Günlük dilde Bitki yapısı olarak bilinen kavram",
      "answer": "SERA"
    },
    {
      "number": 4,
      "direction": "down",
      "row": 3,
      "col": 0,
      "length": 3,
      "clue": "Bulmacada Beyaz besin sıvısı karşılığını veren yanıt",
      "answer": "SÜT"
    },
    {
      "number": 4,
      "direction": "across",
      "row": 3,
      "col": 0,
      "length": 6,
      "clue": "Kısa an anlamına gelen sözcük",
      "answer": "SANİYE"
    },
    {
      "number": 5,
      "direction": "down",
      "row": 4,
      "col": 8,
      "length": 4,
      "clue": "Bulmacada Kırmızı meyve karşılığını veren yanıt",
      "answer": "ELMA"
    },
    {
      "number": 6,
      "direction": "down",
      "row": 4,
      "col": 10,
      "length": 5,
      "clue": "Vaktinden önce karşılığı olarak kullanılan kelime",
      "answer": "ERKEN"
    },
    {
      "number": 7,
      "direction": "across",
      "row": 5,
      "col": 0,
      "length": 3,
      "clue": "Bulmacada Hekimlik bilimi karşılığını veren yanıt",
      "answer": "TIP"
    },
    {
      "number": 8,
      "direction": "across",
      "row": 5,
      "col": 5,
      "length": 4,
      "clue": "Gerçek ya da hakiki için kullanılan yaygın ifade",
      "answer": "ASIL"
    },
    {
      "number": 9,
      "direction": "across",
      "row": 7,
      "col": 7,
      "length": 5,
      "clue": "Bulmacada Yas ya da acı karşılığını veren yanıt",
      "answer": "MATEM"
    }
  ]
}
