{
  "id": 343,
  "title": "Bölüm 343",
  "difficulty": "Zor",
  "grid_size_r": 11,
  "grid_size_c": 9,
  "grid": [
    [
      0,
      0,
      0,
      0,
      0,
      0,
      1,
      0,
      1
    ],
    [
      0,
      0,
      0,
      0,
      0,
      1,
      1,
      1,
      1
    ],
    [
      0,
      0,
      0,
      0,
      0,
      0,
      1,
      0,
      1
    ],
    [
      0,
      0,
      0,
      0,
      0,
      0,
      1,
      0,
      1
    ],
    [
      0,
      0,
      0,
      1,
      1,
      1,
      1,
      0,
      0
    ],
    [
      0,
      0,
      0,
      0,
      0,
      1,
      0,
      0,
      0
    ],
    [
      0,
      0,
      0,
      1,
      1,
      1,
      1,
      0,
      0
    ],
    [
      0,
      1,
      0,
      1,
      0,
      1,
      0,
      0,
      0
    ],
    [
      1,
      1,
      1,
      1,
      0,
      0,
      0,
      0,
      0
    ],
    [
      0,
      1,
      0,
      0,
      0,
      0,
      0,
      0,
      0
    ],
    [
      1,
      1,
      1,
      1,
      0,
      0,
      0,
      0,
      0
    ]
  ],
  "words": [
    {
      "number": 1,
      "direction": "down",
      "row": 0,
      "col": 6,
      "length": 5,
      "clue": "Suda yaşayan canlı karşılığı olarak kullanılan kelime",
      "answer": "BALIK"
    },
    {
      "number": 2,
      "direction": "down",
      "row": 0,
      "col": 8,
      "length": 4,
      "clue": "Günlük dilde Felaket ya da kötülük olarak bilinen kavram",
      "answer": "BELA"
    },
    {
      "number": 3,
      "direction": "across",
      "row": 1,
      "col": 5,
      "length": 4,
      "clue": "Amaç ya da maksat için kullanılan yaygın ifade",
      "answer": "GAYE"
    },
    {
      "number": 4,
      "direction": "across",
      "row": 4,
      "col": 3,
      "length": 4,
      "clue": "Havada uçan taşıt karşılığı olarak kullanılan kelime",
      "answer": "UÇAK"
    },
    {
      "number": 5,
      "direction": "down",
      "row": 4,
      "col": 5,
      "length": 4,
      "clue": "Günlük dilde Düşünme yetisi olarak bilinen kavram",
      "answer": "AKIL"
    },
    {
      "number": 6,
      "direction": "down",
      "row": 6,
      "col": 3,
      "length": 3,
      "clue": "Günlük dilde Bal yapan böcek olarak bilinen kavram",
      "answer": "ARI"
    },
    {
      "number": 6,
      "direction": "across",
      "row": 6,
      "col": 3,
      "length": 4,
      "clue": "Gerçek ya da hakiki için kullanılan yaygın ifade",
      "answer": "ASIL"
    },
    {
      "number": 7,
      "direction": "down",
      "row": 7,
      "col": 1,
      "length": 4,
      "clue": "Talih ya da şans için kullanılan yaygın ifade",
      "answer": "BAHT"
    },
    {
      "number": 8,
      "direction": "across",
      "row": 8,
      "col": 0,
      "length": 4,
      "clue": "Bulmacada Yazılmış metin karşılığını veren yanıt",
      "answer": "YAZI"
    },
    {
      "number": 9,
      "direction": "across",
      "row": 10,
      "col": 0,
      "length": 4,
      "clue": "Bulmacada Konaklama yeri karşılığını veren yanıt",
      "answer": "OTEL"
    }
  ]
}
