{
  "id": 169,
  "title": "Bölüm 169",
  "difficulty": "Orta",
  "grid_size_r": 7,
  "grid_size_c": 10,
  "grid": [
    [
      0,
      0,
      0,
      1,
      0,
      0,
      0,
      1,
      0,
      0
    ],
    [
      1,
      1,
      1,
      1,
      0,
      1,
      0,
      1,
      0,
      0
    ],
    [
      0,
      0,
      0,
      1,
      0,
      1,
      1,
      1,
      1,
      1
    ],
    [
      0,
      1,
      0,
      1,
      1,
      1,
      0,
      0,
      0,
      1
    ],
    [
      1,
      1,
      1,
      1,
      0,
      1,
      0,
      0,
      0,
      1
    ],
    [
      0,
      1,
      0,
      0,
      0,
      0,
      1,
      1,
      1,
      1
    ],
    [
      0,
      1,
      0,
      0,
      0,
      0,
      0,
      0,
      0,
      1
    ]
  ],
  "words": [
    {
      "number": 1,
      "direction": "down",
      "row": 0,
      "col": 3,
      "length": 5,
      "clue": "Bilme isteği için kullanılan yaygın ifade",
      "answer": "MERAK"
    },
    {
      "number": 2,
      "direction": "down",
      "row": 0,
      "col": 7,
      "length": 3,
      "clue": "Evin çatısı anlamına gelen sözcük",
      "answer": "DAM"
    },
    {
      "number": 3,
      "direction": "across",
      "row": 1,
      "col": 0,
      "length": 4,
      "clue": "Karanlık zaman anlamına gelen sözcük",
      "answer": "GECE"
    },
    {
      "number": 4,
      "direction": "down",
      "row": 1,
      "col": 5,
      "length": 4,
      "clue": "Bulmacada Suça yaptırım karşılığını veren yanıt",
      "answer": "CEZA"
    },
    {
      "number": 5,
      "direction": "across",
      "row": 2,
      "col": 5,
      "length": 5,
      "clue": "En sert taş karşılığı olarak kullanılan kelime",
      "answer": "ELMAS"
    },
    {
      "number": 6,
      "direction": "down",
      "row": 2,
      "col": 9,
      "length": 5,
      "clue": "Günün başı anlamına gelen sözcük",
      "answer": "SABAH"
    },
    {
      "number": 7,
      "direction": "down",
      "row": 3,
      "col": 1,
      "length": 4,
      "clue": "Bulmacada Bayat olmayan karşılığını veren yanıt",
      "answer": "TAZE"
    },
    {
      "number": 8,
      "direction": "across",
      "row": 3,
      "col": 3,
      "length": 3,
      "clue": "Sunma ya da takdim anlamına gelen sözcük",
      "answer": "ARZ"
    },
    {
      "number": 9,
      "direction": "across",
      "row": 4,
      "col": 0,
      "length": 4,
      "clue": "Ayrım ya da değişiklik anlamına gelen sözcük",
      "answer": "FARK"
    },
    {
      "number": 10,
      "direction": "across",
      "row": 5,
      "col": 6,
      "length": 4,
      "clue": "Bağlama aracı anlamına gelen sözcük",
      "answer": "TOKA"
    }
  ]
}
