{
  "id": 349,
  "title": "Bölüm 349",
  "difficulty": "Zor",
  "grid_size_r": 11,
  "grid_size_c": 11,
  "grid": [
    [
      0,
      0,
      0,
      0,
      0,
      0,
      1,
      0,
      1,
      0,
      0
    ],
    [
      0,
      0,
      0,
      0,
      0,
      0,
      1,
      1,
      1,
      1,
      0
    ],
    [
      0,
      0,
      0,
      0,
      0,
      0,
      1,
      0,
      1,
      0,
      0
    ],
    [
      0,
      0,
      0,
      0,
      0,
      0,
      0,
      0,
      1,
      0,
      0
    ],
    [
      0,
      0,
      0,
      0,
      0,
      0,
      0,
      0,
      1,
      0,
      0
    ],
    [
      0,
      0,
      0,
      0,
      0,
      0,
      0,
      1,
      1,
      1,
      1
    ],
    [
      0,
      0,
      0,
      0,
      0,
      0,
      0,
      1,
      0,
      0,
      0
    ],
    [
      1,
      0,
      0,
      1,
      0,
      1,
      1,
      1,
      1,
      0,
      0
    ],
    [
      1,
      0,
      0,
      1,
      0,
      1,
      0,
      1,
      0,
      0,
      0
    ],
    [
      1,
      0,
      0,
      1,
      0,
      1,
      0,
      0,
      0,
      0,
      0
    ],
    [
      1,
      1,
      1,
      1,
      1,
      1,
      0,
      0,
      0,
      0,
      0
    ]
  ],
  "words": [
    {
      "number": 1,
      "direction": "down",
      "row": 0,
      "col": 6,
      "length": 3,
      "clue": "Denizden ya da yer altından çıkarılan; yemeklere tat veren beyaz tane.",
      "answer": "TUZ"
    },
    {
      "number": 2,
      "direction": "down",
      "row": 0,
      "col": 8,
      "length": 6,
      "clue": "Harcanan çabaya değmeyen; hiçbir yarar sağlamayan boş uğraş.",
      "answer": "NAFİLE"
    },
    {
      "number": 3,
      "direction": "across",
      "row": 1,
      "col": 6,
      "length": 4,
      "clue": "Aradaki mesafenin çok olduğu; yakınlığı hissedilmeyen ötelerdeki yer.",
      "answer": "UZAK"
    },
    {
      "number": 4,
      "direction": "down",
      "row": 5,
      "col": 7,
      "length": 4,
      "clue": "Suç işleyen kimseye, yaptığının karşılığı olarak verilen yaptırım.",
      "answer": "CEZA"
    },
    {
      "number": 4,
      "direction": "across",
      "row": 5,
      "col": 7,
      "length": 4,
      "clue": "Bir işi başarmak için gösterilen büyük çaba, gayret ve çalışma.",
      "answer": "CEHD"
    },
    {
      "number": 5,
      "direction": "down",
      "row": 7,
      "col": 0,
      "length": 4,
      "clue": "İçten doğan büyük istek; insanı coşturan şiddetli arzu ve heves.",
      "answer": "ŞEVK"
    },
    {
      "number": 6,
      "direction": "down",
      "row": 7,
      "col": 3,
      "length": 4,
      "clue": "Mahkemenin verdiği kararı bildiren, yazılı resmi belge.",
      "answer": "İLAM"
    },
    {
      "number": 7,
      "direction": "across",
      "row": 7,
      "col": 5,
      "length": 4,
      "clue": "Yeni toplanmış, bayatlamamış; canlılığını yeni yeni yitirmemiş olan.",
      "answer": "TAZE"
    },
    {
      "number": 7,
      "direction": "down",
      "row": 7,
      "col": 5,
      "length": 4,
      "clue": "Ekmeğin arasına peynir konup ısıtılarak kızartılan sandviç çeşidi.",
      "answer": "TOST"
    },
    {
      "number": 8,
      "direction": "across",
      "row": 10,
      "col": 0,
      "length": 6,
      "clue": "Kişinin payına düşen; kaderin ona uygun gördüğü nasibi ya da şansı.",
      "answer": "KISMET"
    }
  ]
}
