{
  "id": 288,
  "title": "Bölüm 288",
  "difficulty": "Zor",
  "grid_size_r": 9,
  "grid_size_c": 12,
  "grid": [
    [
      0,
      1,
      0,
      0,
      0,
      0,
      0,
      0,
      0,
      0,
      0,
      0
    ],
    [
      0,
      1,
      0,
      0,
      0,
      0,
      0,
      0,
      0,
      0,
      0,
      0
    ],
    [
      0,
      1,
      0,
      1,
      0,
      1,
      0,
      0,
      0,
      0,
      0,
      0
    ],
    [
      1,
      1,
      1,
      1,
      1,
      1,
      0,
      0,
      0,
      0,
      0,
      0
    ],
    [
      1,
      0,
      0,
      1,
      0,
      1,
      0,
      0,
      1,
      0,
      1,
      0
    ],
    [
      1,
      1,
      1,
      0,
      0,
      1,
      1,
      1,
      1,
      0,
      1,
      0
    ],
    [
      0,
      0,
      0,
      0,
      0,
      0,
      0,
      0,
      1,
      0,
      1,
      0
    ],
    [
      0,
      0,
      0,
      0,
      0,
      0,
      0,
      1,
      1,
      1,
      1,
      1
    ],
    [
      0,
      0,
      0,
      0,
      0,
      0,
      0,
      0,
      0,
      0,
      1,
      0
    ]
  ],
  "words": [
    {
      "number": 1,
      "direction": "down",
      "row": 0,
      "col": 1,
      "length": 4,
      "clue": "İnsanın boynunun üst kısmında bulunan, düşünmenin merkezi olan baş.",
      "answer": "KAFA"
    },
    {
      "number": 2,
      "direction": "down",
      "row": 2,
      "col": 3,
      "length": 3,
      "clue": "Ağızda bulunan, yiyecekleri kopartıp öğütmeye yarayan sert beyaz yapı.",
      "answer": "DİŞ"
    },
    {
      "number": 3,
      "direction": "down",
      "row": 2,
      "col": 5,
      "length": 4,
      "clue": "İçerisi camla kaplı; mevsim dışında bile bitki yetiştirilen ısıtılmış yapı.",
      "answer": "SERA"
    },
    {
      "number": 4,
      "direction": "down",
      "row": 3,
      "col": 0,
      "length": 3,
      "clue": "İnek, keçi gibi memelilerden sağılan; beyaz renkli besleyici temel içecek.",
      "answer": "SÜT"
    },
    {
      "number": 4,
      "direction": "across",
      "row": 3,
      "col": 0,
      "length": 6,
      "clue": "Dakikanın altmışta biri; zamanın en küçük günlük ölçü birimi.",
      "answer": "SANİYE"
    },
    {
      "number": 5,
      "direction": "down",
      "row": 4,
      "col": 8,
      "length": 4,
      "clue": "Kabuğu kırmızı, sarı ya da yeşil olabilen, sulu ve çıtır meyve.",
      "answer": "ELMA"
    },
    {
      "number": 6,
      "direction": "down",
      "row": 4,
      "col": 10,
      "length": 5,
      "clue": "Belirlenen vaktin öncesinde gelme; geç kalmanın tersi durumu.",
      "answer": "ERKEN"
    },
    {
      "number": 7,
      "direction": "across",
      "row": 5,
      "col": 0,
      "length": 3,
      "clue": "Hastalıkların tanısı ve iyileştirilmesiyle uğraşan hekimlik bilim dalı.",
      "answer": "TIP"
    },
    {
      "number": 8,
      "direction": "across",
      "row": 5,
      "col": 5,
      "length": 4,
      "clue": "Sahte ya da taklit olmayan; bir şeyin gerçek ve temel olan hali.",
      "answer": "ASIL"
    },
    {
      "number": 9,
      "direction": "across",
      "row": 7,
      "col": 7,
      "length": 5,
      "clue": "Kaybedilen bir yakının ardından tutulan koyu yas; siyahlar giyme hali.",
      "answer": "MATEM"
    }
  ]
}
