{
  "id": 166,
  "title": "Bölüm 166",
  "difficulty": "Orta",
  "grid_size_r": 9,
  "grid_size_c": 12,
  "grid": [
    [
      0,
      0,
      0,
      0,
      0,
      0,
      0,
      1,
      1,
      1,
      1,
      1
    ],
    [
      0,
      0,
      0,
      0,
      0,
      0,
      0,
      1,
      0,
      0,
      0,
      1
    ],
    [
      0,
      0,
      0,
      0,
      0,
      1,
      0,
      1,
      0,
      0,
      0,
      1
    ],
    [
      0,
      0,
      0,
      0,
      0,
      1,
      1,
      1,
      1,
      1,
      0,
      1
    ],
    [
      0,
      1,
      0,
      1,
      0,
      1,
      0,
      0,
      1,
      0,
      0,
      1
    ],
    [
      0,
      1,
      0,
      1,
      1,
      1,
      1,
      0,
      1,
      0,
      0,
      0
    ],
    [
      0,
      1,
      0,
      1,
      0,
      0,
      0,
      0,
      0,
      0,
      0,
      0
    ],
    [
      1,
      1,
      1,
      1,
      0,
      0,
      0,
      0,
      0,
      0,
      0,
      0
    ],
    [
      0,
      1,
      0,
      0,
      0,
      0,
      0,
      0,
      0,
      0,
      0,
      0
    ]
  ],
  "words": [
    {
      "number": 1,
      "direction": "down",
      "row": 0,
      "col": 7,
      "length": 4,
      "clue": "Anadolu halkı için kullanılan yaygın ifade",
      "answer": "TÜRK"
    },
    {
      "number": 1,
      "direction": "across",
      "row": 0,
      "col": 7,
      "length": 5,
      "clue": "Yemek kabı anlamına gelen sözcük",
      "answer": "TABAK"
    },
    {
      "number": 2,
      "direction": "down",
      "row": 0,
      "col": 11,
      "length": 5,
      "clue": "Günlük dilde Yemek aracı olarak bilinen kavram",
      "answer": "KAŞIK"
    },
    {
      "number": 3,
      "direction": "down",
      "row": 2,
      "col": 5,
      "length": 4,
      "clue": "Günlük dilde Felaket ya da kötülük olarak bilinen kavram",
      "answer": "BELA"
    },
    {
      "number": 4,
      "direction": "across",
      "row": 3,
      "col": 5,
      "length": 5,
      "clue": "Vaktinden önce karşılığı olarak kullanılan kelime",
      "answer": "ERKEN"
    },
    {
      "number": 5,
      "direction": "down",
      "row": 3,
      "col": 8,
      "length": 3,
      "clue": "Tırnak törpüsü için kullanılan yaygın ifade",
      "answer": "EĞE"
    },
    {
      "number": 6,
      "direction": "down",
      "row": 4,
      "col": 1,
      "length": 5,
      "clue": "Bulmacada Suyla ıslanmış karşılığını veren yanıt",
      "answer": "ISLAK"
    },
    {
      "number": 7,
      "direction": "down",
      "row": 4,
      "col": 3,
      "length": 4,
      "clue": "Ev ya da konut karşılığı olarak kullanılan kelime",
      "answer": "HANE"
    },
    {
      "number": 8,
      "direction": "across",
      "row": 5,
      "col": 3,
      "length": 4,
      "clue": "Bulmacada Hedef ya da gaye karşılığını veren yanıt",
      "answer": "AMAÇ"
    },
    {
      "number": 9,
      "direction": "across",
      "row": 7,
      "col": 0,
      "length": 4,
      "clue": "Ferahlatıcı bitki anlamına gelen sözcük",
      "answer": "NANE"
    }
  ]
}
