{
  "id": 135,
  "title": "Bölüm 135",
  "difficulty": "Orta",
  "grid_size_r": 9,
  "grid_size_c": 11,
  "grid": [
    [
      0,
      0,
      0,
      0,
      0,
      0,
      0,
      0,
      0,
      1,
      0
    ],
    [
      0,
      0,
      0,
      1,
      0,
      0,
      0,
      0,
      1,
      1,
      1
    ],
    [
      0,
      0,
      1,
      1,
      1,
      1,
      1,
      0,
      0,
      1,
      0
    ],
    [
      0,
      1,
      0,
      1,
      0,
      0,
      1,
      1,
      1,
      1,
      0
    ],
    [
      0,
      1,
      1,
      1,
      1,
      0,
      1,
      0,
      0,
      0,
      0
    ],
    [
      0,
      1,
      0,
      1,
      0,
      0,
      1,
      0,
      0,
      0,
      0
    ],
    [
      1,
      1,
      1,
      0,
      0,
      0,
      1,
      0,
      0,
      0,
      0
    ],
    [
      0,
      1,
      0,
      0,
      0,
      1,
      1,
      1,
      0,
      0,
      0
    ],
    [
      0,
      1,
      0,
      0,
      0,
      0,
      0,
      0,
      0,
      0,
      0
    ]
  ],
  "words": [
    {
      "number": 1,
      "direction": "down",
      "row": 0,
      "col": 9,
      "length": 4,
      "clue": "Yazılmış metin",
      "answer": "YAZI"
    },
    {
      "number": 2,
      "direction": "down",
      "row": 1,
      "col": 3,
      "length": 5,
      "clue": "Kanatlı kutsal varlık",
      "answer": "MELEK"
    },
    {
      "number": 3,
      "direction": "across",
      "row": 1,
      "col": 8,
      "length": 3,
      "clue": "Göz üstü kıl şeridi",
      "answer": "KAŞ"
    },
    {
      "number": 4,
      "direction": "across",
      "row": 2,
      "col": 2,
      "length": 5,
      "clue": "Bilimsel test",
      "answer": "DENEY"
    },
    {
      "number": 5,
      "direction": "down",
      "row": 2,
      "col": 6,
      "length": 6,
      "clue": "Gökten su damlaları",
      "answer": "YAĞMUR"
    },
    {
      "number": 6,
      "direction": "down",
      "row": 3,
      "col": 1,
      "length": 6,
      "clue": "Ülke yönetimi",
      "answer": "DEVLET"
    },
    {
      "number": 7,
      "direction": "across",
      "row": 3,
      "col": 6,
      "length": 4,
      "clue": "Yemek pişiren",
      "answer": "AŞÇI"
    },
    {
      "number": 8,
      "direction": "across",
      "row": 4,
      "col": 1,
      "length": 4,
      "clue": "Sanat yapıtı",
      "answer": "ESER"
    },
    {
      "number": 9,
      "direction": "across",
      "row": 6,
      "col": 0,
      "length": 3,
      "clue": "Birinci, baştaki",
      "answer": "İLK"
    },
    {
      "number": 10,
      "direction": "across",
      "row": 7,
      "col": 5,
      "length": 3,
      "clue": "Bal yapan böcek",
      "answer": "ARI"
    }
  ]
}