{
  "id": 407,
  "title": "Bölüm 407",
  "difficulty": "Çok Zor",
  "grid_size_r": 12,
  "grid_size_c": 12,
  "grid": [
    [
      0,
      0,
      0,
      0,
      0,
      0,
      1,
      1,
      1,
      1,
      1,
      0
    ],
    [
      0,
      0,
      0,
      1,
      1,
      1,
      1,
      0,
      0,
      1,
      0,
      0
    ],
    [
      0,
      0,
      0,
      0,
      0,
      0,
      1,
      0,
      1,
      1,
      1,
      1
    ],
    [
      0,
      0,
      0,
      0,
      1,
      0,
      1,
      0,
      0,
      1,
      0,
      0
    ],
    [
      0,
      0,
      0,
      1,
      1,
      1,
      1,
      1,
      1,
      0,
      0,
      0
    ],
    [
      0,
      0,
      0,
      0,
      1,
      0,
      0,
      0,
      0,
      0,
      0,
      0
    ],
    [
      0,
      0,
      0,
      0,
      1,
      1,
      1,
      1,
      0,
      0,
      0,
      0
    ],
    [
      0,
      1,
      0,
      0,
      1,
      0,
      0,
      0,
      0,
      0,
      0,
      0
    ],
    [
      1,
      1,
      1,
      1,
      1,
      1,
      0,
      0,
      0,
      0,
      0,
      0
    ],
    [
      0,
      1,
      0,
      0,
      0,
      0,
      0,
      0,
      0,
      0,
      0,
      0
    ],
    [
      0,
      1,
      0,
      0,
      0,
      0,
      0,
      0,
      0,
      0,
      0,
      0
    ],
    [
      0,
      1,
      0,
      0,
      0,
      0,
      0,
      0,
      0,
      0,
      0,
      0
    ]
  ],
  "words": [
    {
      "number": 1,
      "direction": "across",
      "row": 0,
      "col": 6,
      "length": 5,
      "clue": "Yararlanılan, şükür duyulan değerli varlık; insana verilmiş lütuf.",
      "answer": "NİMET"
    },
    {
      "number": 1,
      "direction": "down",
      "row": 0,
      "col": 6,
      "length": 5,
      "clue": "Kötü bakışın bir kimseye uğursuzluk getireceğine duyulan halk inancı.",
      "answer": "NAZAR"
    },
    {
      "number": 2,
      "direction": "down",
      "row": 0,
      "col": 9,
      "length": 4,
      "clue": "Görgü kurallarına uygun davranış; terbiyeli ve ölçülü olma hali.",
      "answer": "EDEP"
    },
    {
      "number": 3,
      "direction": "across",
      "row": 1,
      "col": 3,
      "length": 4,
      "clue": "İçten duyulan gönül rahatlığı; keder bırakmayan tatlı neşe.",
      "answer": "SAFA"
    },
    {
      "number": 4,
      "direction": "across",
      "row": 2,
      "col": 8,
      "length": 4,
      "clue": "Başımızın üstünde uzanan mavi kubbe; yıldızları barındıran gökyüzü.",
      "answer": "SEMA"
    },
    {
      "number": 5,
      "direction": "down",
      "row": 3,
      "col": 4,
      "length": 6,
      "clue": "Dakikanın altmışta biri; zamanın en küçük günlük ölçü birimi.",
      "answer": "SANİYE"
    },
    {
      "number": 6,
      "direction": "across",
      "row": 4,
      "col": 3,
      "length": 6,
      "clue": "Uzakta olan bir sevgiliyi ya da yeri özlemenin içe işleyen duygusu.",
      "answer": "HASRET"
    },
    {
      "number": 7,
      "direction": "across",
      "row": 6,
      "col": 4,
      "length": 4,
      "clue": "Ucu sivri, arkası delikli; dikiş dikmek için ipliği geçiren ince metal araç.",
      "answer": "İĞNE"
    },
    {
      "number": 8,
      "direction": "down",
      "row": 7,
      "col": 1,
      "length": 5,
      "clue": "Bir kimsenin bir şey için yaptığı istek; dile getirilen açık dilek.",
      "answer": "TALEP"
    },
    {
      "number": 9,
      "direction": "across",
      "row": 8,
      "col": 0,
      "length": 6,
      "clue": "Dinde kıyamet sonrası ölülerin toplanacağına inanılan büyük buluşma yeri.",
      "answer": "MAHŞER"
    }
  ]
}
