{
  "id": 128,
  "title": "Bölüm 128",
  "difficulty": "Orta",
  "grid_size_r": 10,
  "grid_size_c": 10,
  "grid": [
    [
      0,
      0,
      0,
      0,
      0,
      0,
      0,
      0,
      1,
      0
    ],
    [
      0,
      0,
      0,
      0,
      0,
      0,
      0,
      1,
      1,
      1
    ],
    [
      0,
      0,
      0,
      0,
      1,
      0,
      1,
      0,
      1,
      0
    ],
    [
      0,
      0,
      0,
      0,
      1,
      1,
      1,
      1,
      1,
      0
    ],
    [
      0,
      0,
      1,
      1,
      1,
      0,
      1,
      0,
      0,
      0
    ],
    [
      0,
      0,
      0,
      0,
      1,
      0,
      1,
      0,
      0,
      0
    ],
    [
      0,
      1,
      1,
      1,
      1,
      0,
      0,
      0,
      0,
      0
    ],
    [
      0,
      1,
      0,
      0,
      1,
      1,
      1,
      1,
      0,
      0
    ],
    [
      1,
      1,
      1,
      0,
      0,
      0,
      0,
      0,
      0,
      0
    ],
    [
      0,
      1,
      0,
      0,
      0,
      0,
      0,
      0,
      0,
      0
    ]
  ],
  "words": [
    {
      "number": 1,
      "direction": "down",
      "row": 0,
      "col": 8,
      "length": 4,
      "clue": "Müzikle hareket karşılığı olarak kullanılan kelime",
      "answer": "DANS"
    },
    {
      "number": 2,
      "direction": "across",
      "row": 1,
      "col": 7,
      "length": 3,
      "clue": "Bulmacada Durum ya da vaziyet karşılığını veren yanıt",
      "answer": "HAL"
    },
    {
      "number": 3,
      "direction": "down",
      "row": 2,
      "col": 4,
      "length": 6,
      "clue": "Yırtıcı büyük kuş için kullanılan yaygın ifade",
      "answer": "KARTAL"
    },
    {
      "number": 4,
      "direction": "down",
      "row": 2,
      "col": 6,
      "length": 4,
      "clue": "Günlük dilde Silahlı kuvvetler olarak bilinen kavram",
      "answer": "ORDU"
    },
    {
      "number": 5,
      "direction": "across",
      "row": 3,
      "col": 4,
      "length": 5,
      "clue": "Günlük dilde Konum bilgisi olarak bilinen kavram",
      "answer": "ADRES"
    },
    {
      "number": 6,
      "direction": "across",
      "row": 4,
      "col": 2,
      "length": 3,
      "clue": "Aynı özellikleri taşıyan canlı grubu",
      "answer": "TÜR"
    },
    {
      "number": 7,
      "direction": "across",
      "row": 6,
      "col": 1,
      "length": 4,
      "clue": "Ödül bardağı anlamına gelen sözcük",
      "answer": "KUPA"
    },
    {
      "number": 7,
      "direction": "down",
      "row": 6,
      "col": 1,
      "length": 4,
      "clue": "Bulmacada Ev bedeli karşılığını veren yanıt",
      "answer": "KIRA"
    },
    {
      "number": 8,
      "direction": "across",
      "row": 7,
      "col": 4,
      "length": 4,
      "clue": "Günlük dilde Türk parası olarak bilinen kavram",
      "answer": "LİRA"
    },
    {
      "number": 9,
      "direction": "across",
      "row": 8,
      "col": 0,
      "length": 3,
      "clue": "Sunma ya da takdim anlamına gelen sözcük",
      "answer": "ARZ"
    }
  ]
}
