{
  "id": 37,
  "title": "Bölüm 37",
  "difficulty": "Kolay",
  "grid_size_r": 10,
  "grid_size_c": 8,
  "grid": [
    [
      0,
      0,
      1,
      0,
      0,
      0,
      0,
      0
    ],
    [
      0,
      1,
      1,
      1,
      1,
      0,
      0,
      0
    ],
    [
      0,
      0,
      1,
      0,
      1,
      0,
      1,
      0
    ],
    [
      0,
      0,
      0,
      0,
      1,
      1,
      1,
      1
    ],
    [
      1,
      1,
      1,
      1,
      1,
      0,
      1,
      0
    ],
    [
      0,
      1,
      0,
      0,
      1,
      0,
      0,
      0
    ],
    [
      0,
      1,
      0,
      0,
      0,
      0,
      0,
      0
    ],
    [
      0,
      1,
      0,
      0,
      1,
      0,
      0,
      0
    ],
    [
      1,
      1,
      1,
      1,
      1,
      0,
      0,
      0
    ],
    [
      0,
      0,
      0,
      0,
      1,
      0,
      0,
      0
    ]
  ],
  "words": [
    {
      "number": 1,
      "direction": "down",
      "row": 0,
      "col": 2,
      "length": 3,
      "clue": "Bulmacada Rüzgar ya da esinti karşılığını veren yanıt",
      "answer": "YEL"
    },
    {
      "number": 2,
      "direction": "across",
      "row": 1,
      "col": 1,
      "length": 4,
      "clue": "Karanlık zaman anlamına gelen sözcük",
      "answer": "GECE"
    },
    {
      "number": 3,
      "direction": "down",
      "row": 1,
      "col": 4,
      "length": 5,
      "clue": "Temel buğday gıdası anlamına gelen sözcük",
      "answer": "EKMEK"
    },
    {
      "number": 4,
      "direction": "down",
      "row": 2,
      "col": 6,
      "length": 3,
      "clue": "Tek renk olmayan, benekli görünüm",
      "answer": "ALA"
    },
    {
      "number": 5,
      "direction": "across",
      "row": 3,
      "col": 4,
      "length": 4,
      "clue": "Günlük dilde Kısa dinlenme olarak bilinen kavram",
      "answer": "MOLA"
    },
    {
      "number": 6,
      "direction": "across",
      "row": 4,
      "col": 0,
      "length": 5,
      "clue": "Evin yeşil alanı anlamına gelen sözcük",
      "answer": "BAHÇE"
    },
    {
      "number": 7,
      "direction": "down",
      "row": 4,
      "col": 1,
      "length": 5,
      "clue": "Bulmacada Dört tekerlekli taşıt karşılığını veren yanıt",
      "answer": "ARABA"
    },
    {
      "number": 8,
      "direction": "down",
      "row": 7,
      "col": 4,
      "length": 3,
      "clue": "Çizgi ya da yol anlamına gelen sözcük",
      "answer": "HAT"
    },
    {
      "number": 9,
      "direction": "across",
      "row": 8,
      "col": 0,
      "length": 5,
      "clue": "Ekin alanı anlamına gelen sözcük",
      "answer": "TARLA"
    }
  ]
}
