{
  "id": 89,
  "title": "Bölüm 89",
  "difficulty": "Çok Zor",
  "grid_size_r": 15,
  "grid_size_c": 16,
  "grid": [
    [
      0,
      0,
      0,
      0,
      1,
      0,
      0,
      1,
      0,
      0,
      1,
      0,
      1,
      0,
      0,
      0
    ],
    [
      0,
      0,
      0,
      0,
      1,
      0,
      1,
      1,
      1,
      1,
      1,
      0,
      1,
      0,
      0,
      0
    ],
    [
      0,
      0,
      0,
      0,
      1,
      0,
      0,
      1,
      0,
      0,
      1,
      1,
      1,
      1,
      1,
      0
    ],
    [
      0,
      0,
      0,
      1,
      1,
      1,
      1,
      1,
      0,
      0,
      1,
      0,
      1,
      0,
      0,
      0
    ],
    [
      0,
      0,
      0,
      0,
      1,
      0,
      0,
      1,
      0,
      1,
      0,
      0,
      1,
      1,
      1,
      1
    ],
    [
      0,
      0,
      0,
      0,
      0,
      1,
      1,
      1,
      1,
      1,
      1,
      0,
      0,
      0,
      0,
      0
    ],
    [
      0,
      0,
      0,
      0,
      0,
      0,
      1,
      0,
      0,
      1,
      0,
      0,
      0,
      0,
      0,
      0
    ],
    [
      0,
      0,
      0,
      0,
      0,
      0,
      1,
      0,
      0,
      1,
      1,
      1,
      1,
      0,
      0,
      0
    ],
    [
      0,
      0,
      0,
      0,
      1,
      1,
      1,
      1,
      1,
      0,
      0,
      0,
      0,
      0,
      0,
      0
    ],
    [
      0,
      0,
      0,
      0,
      0,
      1,
      0,
      0,
      1,
      0,
      0,
      0,
      0,
      0,
      0,
      0
    ],
    [
      1,
      1,
      1,
      1,
      0,
      1,
      0,
      1,
      1,
      1,
      1,
      0,
      0,
      0,
      0,
      0
    ],
    [
      0,
      0,
      1,
      0,
      0,
      1,
      0,
      0,
      1,
      0,
      0,
      0,
      0,
      0,
      0,
      0
    ],
    [
      0,
      0,
      1,
      1,
      1,
      1,
      0,
      0,
      0,
      0,
      0,
      0,
      0,
      0,
      0,
      0
    ],
    [
      0,
      0,
      1,
      0,
      0,
      1,
      0,
      0,
      0,
      0,
      0,
      0,
      0,
      0,
      0,
      0
    ],
    [
      0,
      0,
      0,
      0,
      0,
      1,
      0,
      0,
      0,
      0,
      0,
      0,
      0,
      0,
      0,
      0
    ]
  ],
  "words": [
    {
      "number": 1,
      "direction": "down",
      "row": 0,
      "col": 4,
      "length": 5,
      "clue": "Gölge ağacı",
      "answer": "ÇINAR"
    },
    {
      "number": 2,
      "direction": "down",
      "row": 0,
      "col": 7,
      "length": 6,
      "clue": "Gökten su damlaları",
      "answer": "YAĞMUR"
    },
    {
      "number": 3,
      "direction": "down",
      "row": 0,
      "col": 10,
      "length": 4,
      "clue": "Katlanır bıçak",
      "answer": "ÇAKI"
    },
    {
      "number": 4,
      "direction": "down",
      "row": 0,
      "col": 12,
      "length": 5,
      "clue": "Suda yaşayan canlı",
      "answer": "BALIK"
    },
    {
      "number": 5,
      "direction": "across",
      "row": 1,
      "col": 6,
      "length": 5,
      "clue": "Zar masa oyunu",
      "answer": "TAVLA"
    },
    {
      "number": 6,
      "direction": "across",
      "row": 2,
      "col": 10,
      "length": 5,
      "clue": "Yazı aleti",
      "answer": "KALEM"
    },
    {
      "number": 7,
      "direction": "across",
      "row": 3,
      "col": 3,
      "length": 5,
      "clue": "Maç yöneticisi",
      "answer": "HAKEM"
    },
    {
      "number": 8,
      "direction": "down",
      "row": 4,
      "col": 9,
      "length": 4,
      "clue": "Deniz taşıtı",
      "answer": "GEMİ"
    },
    {
      "number": 9,
      "direction": "across",
      "row": 4,
      "col": 12,
      "length": 4,
      "clue": "Su kabı",
      "answer": "KOVA"
    },
    {
      "number": 10,
      "direction": "across",
      "row": 5,
      "col": 5,
      "length": 6,
      "clue": "Saç kesen esnaf",
      "answer": "BERBER"
    },
    {
      "number": 11,
      "direction": "down",
      "row": 5,
      "col": 6,
      "length": 4,
      "clue": "Sanat yapıtı",
      "answer": "ESER"
    },
    {
      "number": 12,
      "direction": "across",
      "row": 7,
      "col": 9,
      "length": 4,
      "clue": "Kalın olmayan",
      "answer": "İNCE"
    },
    {
      "number": 13,
      "direction": "across",
      "row": 8,
      "col": 4,
      "length": 5,
      "clue": "Ekin alanı",
      "answer": "TARLA"
    },
    {
      "number": 14,
      "direction": "down",
      "row": 8,
      "col": 5,
      "length": 7,
      "clue": "Kilit açma aleti",
      "answer": "ANAHTAR"
    },
    {
      "number": 15,
      "direction": "down",
      "row": 8,
      "col": 8,
      "length": 4,
      "clue": "Gövdeli bitki",
      "answer": "AĞAÇ"
    },
    {
      "number": 16,
      "direction": "across",
      "row": 10,
      "col": 0,
      "length": 4,
      "clue": "Burnun algısı",
      "answer": "KOKU"
    },
    {
      "number": 17,
      "direction": "down",
      "row": 10,
      "col": 2,
      "length": 4,
      "clue": "Miyavlayan evcil",
      "answer": "KEDİ"
    },
    {
      "number": 18,
      "direction": "across",
      "row": 10,
      "col": 7,
      "length": 4,
      "clue": "Rakam ifadesi",
      "answer": "SAYI"
    },
    {
      "number": 19,
      "direction": "across",
      "row": 12,
      "col": 2,
      "length": 4,
      "clue": "Sıkıntı, üzüntü",
      "answer": "DERT"
    }
  ]
}