{
  "id": 255,
  "title": "Bölüm 255",
  "difficulty": "Zor",
  "grid_size_r": 10,
  "grid_size_c": 12,
  "grid": [
    [
      0,
      0,
      0,
      0,
      0,
      0,
      0,
      0,
      0,
      0,
      1,
      0
    ],
    [
      0,
      0,
      0,
      0,
      0,
      0,
      0,
      0,
      0,
      0,
      1,
      0
    ],
    [
      0,
      0,
      1,
      1,
      1,
      1,
      1,
      1,
      0,
      0,
      1,
      0
    ],
    [
      0,
      0,
      0,
      0,
      1,
      0,
      0,
      1,
      1,
      1,
      1,
      1
    ],
    [
      1,
      1,
      1,
      1,
      1,
      0,
      0,
      1,
      0,
      0,
      1,
      0
    ],
    [
      0,
      1,
      0,
      0,
      1,
      1,
      1,
      1,
      1,
      0,
      0,
      0
    ],
    [
      1,
      1,
      1,
      0,
      0,
      0,
      0,
      1,
      0,
      0,
      0,
      0
    ],
    [
      1,
      0,
      0,
      0,
      0,
      0,
      0,
      0,
      0,
      0,
      0,
      0
    ],
    [
      1,
      0,
      0,
      0,
      0,
      0,
      0,
      0,
      0,
      0,
      0,
      0
    ],
    [
      1,
      0,
      0,
      0,
      0,
      0,
      0,
      0,
      0,
      0,
      0,
      0
    ]
  ],
  "words": [
    {
      "number": 1,
      "direction": "down",
      "row": 0,
      "col": 10,
      "length": 5,
      "clue": "Hayal ya da ilüzyon karşılığı olarak kullanılan kelime",
      "answer": "SERAP"
    },
    {
      "number": 2,
      "direction": "across",
      "row": 2,
      "col": 2,
      "length": 6,
      "clue": "Bulmacada Popüler top oyunu karşılığını veren yanıt",
      "answer": "FUTBOL"
    },
    {
      "number": 3,
      "direction": "down",
      "row": 2,
      "col": 4,
      "length": 4,
      "clue": "Anadolu halkı için kullanılan yaygın ifade",
      "answer": "TÜRK"
    },
    {
      "number": 4,
      "direction": "down",
      "row": 2,
      "col": 7,
      "length": 5,
      "clue": "Bulmacada Dil ya da konuşma karşılığını veren yanıt",
      "answer": "LİSAN"
    },
    {
      "number": 5,
      "direction": "across",
      "row": 3,
      "col": 7,
      "length": 5,
      "clue": "Bilme ya da anlayış karşılığı olarak kullanılan kelime",
      "answer": "İRFAN"
    },
    {
      "number": 6,
      "direction": "across",
      "row": 4,
      "col": 0,
      "length": 5,
      "clue": "Bulmacada Katlanma ya da dayanma karşılığını veren yanıt",
      "answer": "SABIR"
    },
    {
      "number": 7,
      "direction": "down",
      "row": 4,
      "col": 1,
      "length": 3,
      "clue": "Bulmacada Koruyucu ilaç karşılığını veren yanıt",
      "answer": "AŞI"
    },
    {
      "number": 8,
      "direction": "across",
      "row": 5,
      "col": 4,
      "length": 5,
      "clue": "Olgunluk için kullanılan yaygın ifade",
      "answer": "KEMAL"
    },
    {
      "number": 9,
      "direction": "across",
      "row": 6,
      "col": 0,
      "length": 3,
      "clue": "Günlük dilde Harici ya da dış yüzey olarak bilinen kavram",
      "answer": "DIŞ"
    },
    {
      "number": 9,
      "direction": "down",
      "row": 6,
      "col": 0,
      "length": 4,
      "clue": "İddia ya da tez karşılığı olarak kullanılan kelime",
      "answer": "DAVA"
    }
  ]
}
